tinterm/__init__.py
tinterm/attributes.py
tinterm/render.py
tinterm/styled.py
tinterm-0.1.0.dist-info/licenses/LICENSE
tinterm-0.1.0.dist-info/METADATA
tinterm-0.1.0.dist-info/WHEEL
tinterm-0.1.0.dist-info/top_level.txt
tinterm-0.1.0.dist-info/RECORD
