Metadata-Version: 2.4
Name: tinterm
Version: 0.1.0
Summary: A lightweight Python library for coloring terminal output with zero dependencies.
Author: Tobias Hafner
License:                                  Apache License
Project-URL: Homepage, https://github.com/TobiasHafner/tinterm
Requires-Python: >=3.9
License-File: LICENSE
Requires-Dist: colorama; platform_system == "Windows"
Provides-Extra: dev
Requires-Dist: pytest>=9.0.2; extra == "dev"
Dynamic: license-file
